LatexGeneratorAP2024/__init__.py
LatexGeneratorAP2024/latexgenerator.py
LatexGenerator_AP2024-1.0.dist-info/METADATA
LatexGenerator_AP2024-1.0.dist-info/WHEEL
LatexGenerator_AP2024-1.0.dist-info/top_level.txt
LatexGenerator_AP2024-1.0.dist-info/RECORD
